roundai/__init__.py
roundai/round.py
roundai-0.1.0.dist-info/METADATA
roundai-0.1.0.dist-info/WHEEL
roundai-0.1.0.dist-info/licenses/LICENSE
roundai-0.1.0.dist-info/RECORD
