Metadata-Version: 2.4
Name: roundai
Version: 0.1.0
Summary: A smart rounding library that rounds numbers from right to left
Project-URL: Homepage, https://github.com/yourusername/roundai
Project-URL: Bug Tracker, https://github.com/yourusername/roundai/issues
Author-email: Your Name <your.email@example.com>
License: MIT License
License-File: LICENSE
Keywords: decimal,math,numeric,round,rounding
Classifier: License :: OSI Approved :: MIT License
Classifier: Operating System :: OS Independent
Classifier: Programming Language :: Python :: 3
Classifier: Programming Language :: Python :: 3.7
Classifier: Programming Language :: Python :: 3.8
Classifier: Programming Language :: Python :: 3.9
Classifier: Programming Language :: Python :: 3.10
Classifier: Programming Language :: Python :: 3.11
Requires-Python: >=3.7
Provides-Extra: test
Requires-Dist: pytest-cov>=2.0; extra == 'test'
Requires-Dist: pytest>=6.0; extra == 'test'
